core/__init__.py
core/analyzer.py
core/backend_client.py
core/capture.py
core/daily_aggregator.py
core/database.py
core/email_reporter.py
core/fallback_handler.py
core/firebase_auth.py
core/goal_manager.py
core/macos_permissions.py
core/onboarding.py
core/query_engine.py
core/service_daemon.py
core/session_builder.py
core/trial_manager.py
telos_tracker/__init__.py
telos_tracker/cli.py
tui/__init__.py
tui/app.py
tui/tutorial.py
tui/models/__init__.py
tui/models/tui_state.py
tui/screens/__init__.py
tui/screens/chat.py
tui/screens/dashboard.py
tui/screens/feedback_modal.py
tui/screens/goal_editor.py
tui/screens/goal_setup.py
tui/screens/help.py
tui/screens/personal_setup.py
tui/screens/privacy_notice.py
tui/screens/settings.py
tui/screens/summary.py
tui/screens/timeline.py
tui/screens/upgrade.py
tui/screens/upgrade_modal.py
tui/screens/welcome.py
tui/screens/welcome_carousel.py
tui/screens/zen_complete.py
tui/widgets/__init__.py
tui/widgets/activity_waveform.py
tui/widgets/category_breakdown.py
tui/widgets/current_activity.py
tui/widgets/day_heatmap.py
tui/widgets/recent_timeline.py
tui/widgets/status_banner.py
tui/widgets/trial_banner.py
tui/workers/__init__.py
tui/workers/capture_worker.py
tui/workers/db_poller.py
tui/workers/email_worker.py
tui/workers/session_worker.py
utils/__init__.py
utils/config_manager.py
utils/hash_utils.py
utils/prompt_loader.py
utils/time_utils.py
telos_tracker/config.yaml.example
telos_tracker/main.py
telos_tracker/prompts/README.md
telos_tracker/prompts/ai_chat_system.txt
telos_tracker/prompts/daily_summary.txt
telos_tracker/prompts/screenshot_analysis.txt
telos_tracker/prompts/session_enrichment.txt
telos_tracker/service.py
telos_tracker/service_macos.py
telos_tracker-0.1.9.dist-info/METADATA
telos_tracker-0.1.9.dist-info/WHEEL
telos_tracker-0.1.9.dist-info/entry_points.txt
telos_tracker-0.1.9.dist-info/RECORD
