Metadata-Version: 2.4
Name: telos-tracker
Version: 0.1.9
Summary: AI-powered screen time tracker with intelligent activity analysis. Install: pip install telos-tracker && telos setup
Project-URL: Homepage, https://github.com/yourusername/telos
Project-URL: Documentation, https://github.com/yourusername/telos#readme
Project-URL: Repository, https://github.com/yourusername/telos
Project-URL: Issues, https://github.com/yourusername/telos/issues
Author-email: Telos Team <hello@telos.app>
License-Expression: MIT
Keywords: activity-tracking,ai,gemini,productivity,screen-time,time-management,tracker
Classifier: Development Status :: 4 - Beta
Classifier: Environment :: Console
Classifier: Intended Audience :: End Users/Desktop
Classifier: License :: OSI Approved :: MIT License
Classifier: Operating System :: OS Independent
Classifier: Programming Language :: Python :: 3
Classifier: Programming Language :: Python :: 3.8
Classifier: Programming Language :: Python :: 3.9
Classifier: Programming Language :: Python :: 3.10
Classifier: Programming Language :: Python :: 3.11
Classifier: Programming Language :: Python :: 3.12
Classifier: Topic :: Office/Business
Classifier: Topic :: System :: Monitoring
Requires-Python: >=3.8
Requires-Dist: google-genai>=1.0.0
Requires-Dist: imagehash>=4.3.1
Requires-Dist: mss>=9.0.1
Requires-Dist: pillow>=10.1.0
Requires-Dist: pynput>=1.7.6
Requires-Dist: pywin32>=306; sys_platform == 'win32'
Requires-Dist: pyyaml>=6.0.1
Requires-Dist: requests>=2.31.0
Requires-Dist: rich>=13.7.0
Requires-Dist: textual>=0.47.0
Provides-Extra: dev
Requires-Dist: black>=23.0.0; extra == 'dev'
Requires-Dist: flake8>=6.0.0; extra == 'dev'
Requires-Dist: pytest>=7.0.0; extra == 'dev'
